LICENSE
MANIFEST.in
README.rst
setup.py
django_mobility.egg-info/PKG-INFO
django_mobility.egg-info/SOURCES.txt
django_mobility.egg-info/dependency_links.txt
django_mobility.egg-info/not-zip-safe
django_mobility.egg-info/requires.txt
django_mobility.egg-info/top_level.txt
mobility/__init__.py
mobility/decorators.py
mobility/middleware.py
mobility/tests.py