Metadata-Version: 1.0
Name: django-mobility
Version: 0.1
Summary: Middleware and decorators for directing users to your mobile site.
Home-page: http://github.com/jbalogh/django-mobility
Author: Jeff Balogh
Author-email: jbalogh@mozilla.com
License: BSD
Platform: UNKNOWN
Classifier: Development Status :: 4 - Beta
Classifier: Environment :: Web Environment
Classifier: Environment :: Web Environment :: Mozilla
Classifier: Framework :: Django
Classifier: Intended Audience :: Developers
Classifier: License :: OSI Approved :: BSD License
Classifier: Operating System :: OS Independent
Classifier: Programming Language :: Python
Classifier: Topic :: Software Development :: Libraries :: Python Modules
